deepART/__init__.py
deepART/dataset/__init__.py
deepART/dataset/gen_dataset.py
deepART/metrics/__init__.py
deepART/nlp/__init__.py
deepART/nlp/chunker/__init__.py
deepART/nlp/cooc_vec/__init__.py
deepART/torch/__init__.py
deepART-0.5.0.dist-info/LICENSE
deepART-0.5.0.dist-info/METADATA
deepART-0.5.0.dist-info/WHEEL
deepART-0.5.0.dist-info/top_level.txt
deepART-0.5.0.dist-info/RECORD
