Metadata-Version: 2.1
Name: deepART
Version: 0.5.0
Summary: A library for family of adaptive resonance theory neural networks
Home-page: UNKNOWN
Author: Chun Ping Lim
Author-email: chunplim@deloitte.com
License: MIT
Platform: UNKNOWN
Classifier: Programming Language :: Python :: 3
Classifier: License :: OSI Approved :: MIT License
Classifier: Operating System :: OS Independent
Requires-Dist: numpy (==1.15.1)
Requires-Dist: joblib (==0.13.0)
Requires-Dist: nltk (==3.4)
